emote_utils/__init__.py
emote_utils-2.0.1.dist-info/AUTHORS
emote_utils-2.0.1.dist-info/LICENSE
emote_utils-2.0.1.dist-info/METADATA
emote_utils-2.0.1.dist-info/WHEEL
emote_utils-2.0.1.dist-info/pbr.json
emote_utils-2.0.1.dist-info/top_level.txt
emote_utils-2.0.1.dist-info/RECORD
