Metadata-Version: 2.1
Name: emote-utils
Version: 2.0.1
Summary: Emote utilities for text-based games.
Home-page: https://github.com/chrisnorman7/
Author: Chris Norman
Author-email: chris.norman2@googlemail.com
License: MPL-2
Platform: UNKNOWN
Requires-Dist: attrs
